funcing-1.0.0.dist-info/licenses/LICENSE
tests/__init__.py
tests/test_core.py
tests/test_examples.py
funcing-1.0.0.dist-info/METADATA
funcing-1.0.0.dist-info/WHEEL
funcing-1.0.0.dist-info/top_level.txt
funcing-1.0.0.dist-info/RECORD
